{
  "name": "c-toural",
  "version": "1.0.0",
  "description": "",
  "main": "index.js",
  "scripts": {
    "lint-ts": "tslint --fix -p tsconfig.json -c tslint.json",
    "lint": "cross-env LINT=1 eslint --fix --ext .js,.ts assets",
    "test": "echo \"Error: no test specified\" && exit 1"
  },
  "husky": {
    "hooks": {
      "pre-commit": "npm run lint-ts"
    }
  },
  "lint-staged": {
    "*.{js,jsx,ts,tsx}": [
      "tslint --fix -p tsconfig.json -c tslint.json",
      "pretty-quick --staged",
      "git add"
    ]
  },
  "repository": {
    "type": "git",
    "url": "git+https://github.com/1166544/c-toural.git"
  },
  "author": "James Liauw",
  "license": "ISC",
  "bugs": {
    "url": "https://github.com/1166544/c-toural/issues"
  },
  "homepage": "https://github.com/1166544/c-toural#readme",
  "devDependencies": {
    "@typescript-eslint/eslint-plugin": "^3.7.0",
    "@typescript-eslint/parser": "^3.7.0",
    "babel-eslint": "^10.1.0",
    "cross-env": "^7.0.2",
    "eslint": "^7.5.0",
    "eslint-config-airbnb-base": "^14.2.0",
    "eslint-config-alloy": "^3.7.4",
    "eslint-config-prettier": "^6.11.0",
    "eslint-plugin-import": "^2.21.2",
    "eslint-plugin-jsdoc": "^30.0.3",
    "husky": "^4.2.5",
    "lint-staged": "^10.2.11",
    "prettier": "^2.0.5",
    "pretty-quick": "^2.0.1",
    "typescript": "^3.9.7"
  },
  "dependencies": {},
  "engines": {
    "node": "^12.14.0"
  }
}
